PWM/pwm_core.v
module pwm_core (
           input rstn,
           input clk,
           output reg pwm,
           input [31 : 0] cycle,
           input [31 : 0] high_level_cycle);

reg [31 : 0] pwm_counter;
always @(posedge clk) begin
    if ((!rstn)) begin
        pwm_counter <= 32'h0;
    end
    else begin
        if (pwm_counter < cycle - 1) begin
            pwm_counter <= pwm_counter + 1;
        end
        else begin
            pwm_counter <= 32'h0;
        end
    end
end

always @( * ) begin
    if (!rstn) begin
        pwm = 0;
    end
    else begin
        if (pwm_counter < high_level_cycle - 1) begin
            pwm = 1;
        end
        else begin
            pwm = 0;
        end
    end
end

endmodule

PWM/axi_lite_pwm.v
module axi_lite_pwm (
           input axi_lite_aclk,
           input axi_lite_aresetn,

           //PWM
           output pwm,

           //AXI Lite interface
           input [31 : 0] axi_lite_awaddr,
           input axi_lite_awvalid,
           output reg axi_lite_awready,

           input [31 : 0] axi_lite_wdata,
           input axi_lite_wvalid,
           output reg axi_lite_wready,

           output reg [1 : 0] axi_lite_bresp,
           output reg axi_lite_bvalid,
           input axi_lite_bready
       );

reg [7 : 0] state;
reg [7 : 0] state_next;
parameter STATE_RESET = 8'h0;
parameter STATE_IDEL = 8'h1;
parameter STATE_WRITE_REG = 8'h3;
parameter STATE_WRITE_BUF = 8'h4;
parameter STATE_CALC = 8'h5;
parameter STATE_RESP = 8'h6;

always @(posedge axi_lite_aclk) begin
    if (!axi_lite_aresetn) begin
        state <= STATE_RESET;
    end
    else begin
        state <= state_next;
    end
end

reg [31 : 0] addr_buf;
reg [31 : 0] data_buf;
reg [1 : 0] resp_buf;

reg [31 : 0] clk_freq_base;
reg [31 : 0] clk_freq_coefficient;
/*
[clock frequence] = clk_freq_base * (2 ^ clk_freq_coefficient)
*/
reg [31 : 0] pwm_frequence;
reg [31 : 0] duty;

always @( * ) begin
    case (state)
        STATE_RESET: begin
            state_next = STATE_IDEL;
        end

        STATE_IDEL: begin
            if (axi_lite_awvalid) begin
                state_next = STATE_WRITE_REG;
            end
            else begin
                state_next = STATE_IDEL;
            end
        end

        STATE_WRITE_REG: begin
            if (axi_lite_wvalid) begin
                state_next = STATE_WRITE_BUF;
            end
            else begin
                state_next = STATE_WRITE_REG;
            end
        end

        STATE_WRITE_BUF: begin
            if ((clk_freq_base == 32'h0) || (clk_freq_coefficient == 32'h0) || (pwm_frequence == 32'h0) || (duty == 32'h0)) begin
                state_next = STATE_IDEL;
            end
            else begin
                state_next = STATE_CALC;
            end
        end

        STATE_CALC: begin
            state_next = STATE_RESP;
        end

        STATE_RESP: begin
            if (axi_lite_bready) begin
                state_next = STATE_IDEL;
            end
            else begin
                state_next = STATE_RESP;
            end
        end

        default: begin

        end
    endcase
end

reg [31 : 0] cycle;
reg [31 : 0] high_level_cycle;

pwm_core pwm_core_inst(
             .rstn(axi_lite_aresetn),
             .clk(axi_lite_aclk),
             .pwm(pwm),
             .cycle(cycle),
             .high_level_cycle(high_level_cycle)
         );

always @( * ) begin
    case (state)
        STATE_RESET: begin
            axi_lite_awready = 0;
            axi_lite_wready = 0;
            axi_lite_bvalid = 0;

            axi_lite_bresp = 2'b0;

            cycle = 100;
            high_level_cycle = 10;

            addr_buf = 32'h0;
            data_buf = 32'h0;
            resp_buf = 2'b0;

            clk_freq_base = 32'h0;
            clk_freq_coefficient = 32'h0;
            pwm_frequence = 32'h0;
            duty = 32'h0;
        end

        STATE_IDEL: begin
            axi_lite_awready = 1;
            axi_lite_wready = 0;
            axi_lite_bvalid = 0;

            axi_lite_bresp = 2'b0;

            data_buf = 32'h0;
            resp_buf = 2'b0;

            if (axi_lite_awvalid) begin
                addr_buf = axi_lite_awaddr;
            end
            else begin
                addr_buf = 32'h0;
            end
        end

        STATE_WRITE_REG: begin
            axi_lite_awready = 0;
            axi_lite_wready = 1;

            if (axi_lite_wvalid) begin
                data_buf = axi_lite_wdata;
            end
            else begin
                data_buf = 32'b0;
            end
        end

        STATE_WRITE_BUF: begin
            case (addr_buf)
                32'h0000_0000: begin
                    clk_freq_base = data_buf;
                    resp_buf = 2'b01;
                end

                32'h0000_0004: begin
                    clk_freq_coefficient = data_buf;
                    resp_buf = 2'b01;
                end

                32'h0000_0008: begin
                    pwm_frequence = data_buf;
                    resp_buf = 2'b01;
                end

                32'h0000_000c: begin
                    duty = data_buf;
                    resp_buf = 2'b01;
                end

                default: begin
                    resp_buf = 2'b10;
                end
            endcase
        end

        STATE_CALC: begin
            cycle = (clk_freq_base << clk_freq_coefficient) / pwm_frequence;
            high_level_cycle = cycle * 100 / duty;
        end

        STATE_RESP: begin
            if (axi_lite_bready) begin
                axi_lite_bresp = resp_buf;
            end
            else begin
                axi_lite_bresp = 2'b0;
            end
        end

        default: begin
            axi_lite_awready = 0;
            axi_lite_wready = 0;
            axi_lite_bvalid = 0;

            axi_lite_bresp = 2'b0;

            cycle = 100;
            high_level_cycle = 10;

            addr_buf = 32'h0;
            data_buf = 32'h0;
            resp_buf = 2'b0;

            clk_freq_base = 32'h0;
            clk_freq_coefficient = 32'h0;
            pwm_frequence = 32'h0;
            duty = 32'h0;
        end
    endcase
end

endmodule

PWM/bench.v
module bench ();

initial begin
    $dumpfile("test.vcd");
    $dumpvars;
end

reg clk = 0;
always #1 clk = ~clk;

reg rstn = 1;
wire pwm;

reg [31 : 0] axi_lite_awaddr;
reg axi_lite_awvalid;
wire axi_lite_awready;

reg [31 : 0] axi_lite_wdata;
reg axi_lite_wvalid;
wire axi_lite_wready;

wire [1 : 0] axi_lite_bresp;
wire axi_lite_bvalid;
reg axi_lite_bready;

axi_lite_pwm axi_lite_pwm_inst
             (
                 .axi_lite_aclk(clk),
                 .axi_lite_aresetn(rstn),

                 .pwm(pwm),

                 .axi_lite_awaddr(axi_lite_awaddr),
                 .axi_lite_awvalid(axi_lite_awvalid),
                 .axi_lite_awready(axi_lite_awready),

                 .axi_lite_wdata(axi_lite_wdata),
                 .axi_lite_wvalid(axi_lite_wvalid),
                 .axi_lite_wready(axi_lite_wready),

                 .axi_lite_bresp(axi_lite_bresp),
                 .axi_lite_bvalid(axi_lite_bvalid),
                 .axi_lite_bready(axi_lite_bready)
             );

event init;
always @(init) begin
    axi_lite_awaddr = 32'h0;
    axi_lite_awvalid = 0;
    axi_lite_wdata = 32'h0;
    axi_lite_wvalid = 0;
    axi_lite_bready = 0;
end

reg [31 : 0] addr;
reg [31 : 0] data;
reg [1 : 0] errno;

event write_reg;
always @(write_reg) begin
    errno = 2'b0;

    #10
     if (axi_lite_awready) begin
         axi_lite_awaddr = addr;
         axi_lite_awvalid = 1;
     end
     #2 -> init;

    #10
     if (axi_lite_wready) begin
         axi_lite_wdata = data;
         axi_lite_wvalid = 1;
     end
     #2 -> init;

    #10
     axi_lite_bready = 1;
    if (axi_lite_bvalid) begin
        errno = axi_lite_bresp;
    end
    #2 -> init;
end

initial begin
    #10 rstn = 0;
    -> init;
    #100 rstn = 1;

    #1000
     addr = 32'h0000_0000;
    data = 32'h02e9_0edd;
    ->write_reg;

    #1000
     addr = 32'h0000_0004;
    data = 32'd10;
    ->write_reg;

    #1000
     addr = 32'h0000_0008;
    data = 32'd10000;
    ->write_reg;

    #1000
     addr = 32'h0000_000c;
    data = 32'd5000;
    ->write_reg;

    #10000
     $stop;
end

endmodule

PWM/test.vcd
$date
	Sat Sep 03 09:44:09 2022
$end
$version
	Icarus Verilog
$end
$timescale
	1s
$end
$scope module bench $end
$var event 1 ! write_reg $end
$var event 1 " init $end
$var wire 1 # pwm $end
$var wire 1 $ axi_lite_wready $end
$var wire 1 % axi_lite_bvalid $end
$var wire 2 & axi_lite_bresp [1:0] $end
$var wire 1 ' axi_lite_awready $end
$var reg 32 ( addr [31:0] $end
$var reg 32 ) axi_lite_awaddr [31:0] $end
$var reg 1 * axi_lite_awvalid $end
$var reg 1 + axi_lite_bready $end
$var reg 32 , axi_lite_wdata [31:0] $end
$var reg 1 - axi_lite_wvalid $end
$var reg 1 . clk $end
$var reg 32 / data [31:0] $end
$var reg 2 0 errno [1:0] $end
$var reg 1 1 rstn $end
$scope module axi_lite_pwm_inst $end
$var wire 1 . axi_lite_aclk $end
$var wire 1 1 axi_lite_aresetn $end
$var wire 32 2 axi_lite_awaddr [31:0] $end
$var wire 1 * axi_lite_awvalid $end
$var wire 1 + axi_lite_bready $end
$var wire 32 3 axi_lite_wdata [31:0] $end
$var wire 1 - axi_lite_wvalid $end
$var wire 1 # pwm $end
$var reg 32 4 addr_buf [31:0] $end
$var reg 1 ' axi_lite_awready $end
$var reg 2 5 axi_lite_bresp [1:0] $end
$var reg 1 % axi_lite_bvalid $end
$var reg 1 $ axi_lite_wready $end
$var reg 32 6 clk_freq_base [31:0] $end
$var reg 32 7 clk_freq_coefficient [31:0] $end
$var reg 32 8 cycle [31:0] $end
$var reg 32 9 data_buf [31:0] $end
$var reg 32 : duty [31:0] $end
$var reg 32 ; high_level_cycle [31:0] $end
$var reg 32 < pwm_frequence [31:0] $end
$var reg 2 = resp_buf [1:0] $end
$var reg 8 > state [7:0] $end
$var reg 8 ? state_next [7:0] $end
$scope module pwm_core_inst $end
$var wire 1 . clk $end
$var wire 32 @ cycle [31:0] $end
$var wire 32 A high_level_cycle [31:0] $end
$var wire 1 1 rstn $end
$var reg 1 # pwm $end
$var reg 32 B pwm_counter [31:0] $end
$upscope $end
$upscope $end
$upscope $end
$enddefinitions $end
#0
$dumpvars
bx B
bx A
bx @
bx ?
bx >
bx =
bx <
bx ;
bx :
bx 9
bx 8
bx 7
bx 6
bx 5
bx 4
bx 3
bx 2
11
bx 0
bx /
0.
x-
bx ,
x+
x*
bx )
bx (
x'
bx &
x%
x$
0#
1"
1!
$end
#1
b0 B
1.
#2
0.
#3
1.
#4
0.
#5
1.
#6
0.
#7
1.
#8
0.
#9
1.
#10
b0 :
b0 <
b0 7
b0 6
b0 =
b0 9
b0 4
b1010 ;
b1010 A
b1100100 8
b1100100 @
b0 &
b0 5
0%
0$
0'
0+
0-
b0 ,
b0 3
0*
b0 )
b0 2
0.
1"
01
#11
b1 ?
b0 >
1.
#12
0.
#13
1.
#14
0.
#15
1.
#16
0.
#17
1.
#18
0.
#19
1.
#20
0.
#21
1.
#22
0.
#23
1.
#24
0.
#25
1.
#26
0.
#27
1.
#28
0.
#29
1.
#30
0.
#31
1.
#32
0.
#33
1.
#34
0.
#35
1.
#36
0.
#37
1.
#38
0.
#39
1.
#40
0.
#41
1.
#42
0.
#43
1.
#44
0.
#45
1.
#46
0.
#47
1.
#48
0.
#49
1.
#50
0.
#51
1.
#52
0.
#53
1.
#54
0.
#55
1.
#56
0.
#57
1.
#58
0.
#59
1.
#60
0.
#61
1.
#62
0.
#63
1.
#64
0.
#65
1.
#66
0.
#67
1.
#68
0.
#69
1.
#70
0.
#71
1.
#72
0.
#73
1.
#74
0.
#75
1.
#76
0.
#77
1.
#78
0.
#79
1.
#80
0.
#81
1.
#82
0.
#83
1.
#84
0.
#85
1.
#86
0.
#87
1.
#88
0.
#89
1.
#90
0.
#91
1.
#92
0.
#93
1.
#94
0.
#95
1.
#96
0.
#97
1.
#98
0.
#99
1.
#100
0.
#101
1.
#102
0.
#103
1.
#104
0.
#105
1.
#106
0.
#107
1.
#108
0.
#109
1.
#110
1#
0.
11
#111
1'
b1 >
b1 B
1.
#112
0.
#113
b10 B
1.
#114
0.
#115
b11 B
1.
#116
0.
#117
b100 B
1.
#118
0.
#119
b101 B
1.
#120
0.
#121
b110 B
1.
#122
0.
#123
b111 B
1.
#124
0.
#125
b1000 B
1.
#126
0.
#127
0#
b1001 B
1.
#128
0.
#129
b1010 B
1.
#130
0.
#131
b1011 B
1.
#132
0.
#133
b1100 B
1.
#134
0.
#135
b1101 B
1.
#136
0.
#137
b1110 B
1.
#138
0.
#139
b1111 B
1.
#140
0.
#141
b10000 B
1.
#142
0.
#143
b10001 B
1.
#144
0.
#145
b10010 B
1.
#146
0.
#147
b10011 B
1.
#148
0.
#149
b10100 B
1.
#150
0.
#151
b10101 B
1.
#152
0.
#153
b10110 B
1.
#154
0.
#155
b10111 B
1.
#156
0.
#157
b11000 B
1.
#158
0.
#159
b11001 B
1.
#160
0.
#161
b11010 B
1.
#162
0.
#163
b11011 B
1.
#164
0.
#165
b11100 B
1.
#166
0.
#167
b11101 B
1.
#168
0.
#169
b11110 B
1.
#170
0.
#171
b11111 B
1.
#172
0.
#173
b100000 B
1.
#174
0.
#175
b100001 B
1.
#176
0.
#177
b100010 B
1.
#178
0.
#179
b100011 B
1.
#180
0.
#181
b100100 B
1.
#182
0.
#183
b100101 B
1.
#184
0.
#185
b100110 B
1.
#186
0.
#187
b100111 B
1.
#188
0.
#189
b101000 B
1.
#190
0.
#191
b101001 B
1.
#192
0.
#193
b101010 B
1.
#194
0.
#195
b101011 B
1.
#196
0.
#197
b101100 B
1.
#198
0.
#199
b101101 B
1.
#200
0.
#201
b101110 B
1.
#202
0.
#203
b101111 B
1.
#204
0.
#205
b110000 B
1.
#206
0.
#207
b110001 B
1.
#208
0.
#209
b110010 B
1.
#210
0.
#211
b110011 B
1.
#212
0.
#213
b110100 B
1.
#214
0.
#215
b110101 B
1.
#216
0.
#217
b110110 B
1.
#218
0.
#219
b110111 B
1.
#220
0.
#221
b111000 B
1.
#222
0.
#223
b111001 B
1.
#224
0.
#225
b111010 B
1.
#226
0.
#227
b111011 B
1.
#228
0.
#229
b111100 B
1.
#230
0.
#231
b111101 B
1.
#232
0.
#233
b111110 B
1.
#234
0.
#235
b111111 B
1.
#236
0.
#237
b1000000 B
1.
#238
0.
#239
b1000001 B
1.
#240
0.
#241
b1000010 B
1.
#242
0.
#243
b1000011 B
1.
#244
0.
#245
b1000100 B
1.
#246
0.
#247
b1000101 B
1.
#248
0.
#249
b1000110 B
1.
#250
0.
#251
b1000111 B
1.
#252
0.
#253
b1001000 B
1.
#254
0.
#255
b1001001 B
1.
#256
0.
#257
b1001010 B
1.
#258
0.
#259
b1001011 B
1.
#260
0.
#261
b1001100 B
1.
#262
0.
#263
b1001101 B
1.
#264
0.
#265
b1001110 B
1.
#266
0.
#267
b1001111 B
1.
#268
0.
#269
b1010000 B
1.
#270
0.
#271
b1010001 B
1.
#272
0.
#273
b1010010 B
1.
#274
0.
#275
b1010011 B
1.
#276
0.
#277
b1010100 B
1.
#278
0.
#279
b1010101 B
1.
#280
0.
#281
b1010110 B
1.
#282
0.
#283
b1010111 B
1.
#284
0.
#285
b1011000 B
1.
#286
0.
#287
b1011001 B
1.
#288
0.
#289
b1011010 B
1.
#290
0.
#291
b1011011 B
1.
#292
0.
#293
b1011100 B
1.
#294
0.
#295
b1011101 B
1.
#296
0.
#297
b1011110 B
1.
#298
0.
#299
b1011111 B
1.
#300
0.
#301
b1100000 B
1.
#302
0.
#303
b1100001 B
1.
#304
0.
#305
b1100010 B
1.
#306
0.
#307
b1100011 B
1.
#308
0.
#309
1#
b0 B
1.
#310
0.
#311
b1 B
1.
#312
0.
#313
b10 B
1.
#314
0.
#315
b11 B
1.
#316
0.
#317
b100 B
1.
#318
0.
#319
b101 B
1.
#320
0.
#321
b110 B
1.
#322
0.
#323
b111 B
1.
#324
0.
#325
b1000 B
1.
#326
0.
#327
0#
b1001 B
1.
#328
0.
#329
b1010 B
1.
#330
0.
#331
b1011 B
1.
#332
0.
#333
b1100 B
1.
#334
0.
#335
b1101 B
1.
#336
0.
#337
b1110 B
1.
#338
0.
#339
b1111 B
1.
#340
0.
#341
b10000 B
1.
#342
0.
#343
b10001 B
1.
#344
0.
#345
b10010 B
1.
#346
0.
#347
b10011 B
1.
#348
0.
#349
b10100 B
1.
#350
0.
#351
b10101 B
1.
#352
0.
#353
b10110 B
1.
#354
0.
#355
b10111 B
1.
#356
0.
#357
b11000 B
1.
#358
0.
#359
b11001 B
1.
#360
0.
#361
b11010 B
1.
#362
0.
#363
b11011 B
1.
#364
0.
#365
b11100 B
1.
#366
0.
#367
b11101 B
1.
#368
0.
#369
b11110 B
1.
#370
0.
#371
b11111 B
1.
#372
0.
#373
b100000 B
1.
#374
0.
#375
b100001 B
1.
#376
0.
#377
b100010 B
1.
#378
0.
#379
b100011 B
1.
#380
0.
#381
b100100 B
1.
#382
0.
#383
b100101 B
1.
#384
0.
#385
b100110 B
1.
#386
0.
#387
b100111 B
1.
#388
0.
#389
b101000 B
1.
#390
0.
#391
b101001 B
1.
#392
0.
#393
b101010 B
1.
#394
0.
#395
b101011 B
1.
#396
0.
#397
b101100 B
1.
#398
0.
#399
b101101 B
1.
#400
0.
#401
b101110 B
1.
#402
0.
#403
b101111 B
1.
#404
0.
#405
b110000 B
1.
#406
0.
#407
b110001 B
1.
#408
0.
#409
b110010 B
1.
#410
0.
#411
b110011 B
1.
#412
0.
#413
b110100 B
1.
#414
0.
#415
b110101 B
1.
#416
0.
#417
b110110 B
1.
#418
0.
#419
b110111 B
1.
#420
0.
#421
b111000 B
1.
#422
0.
#423
b111001 B
1.
#424
0.
#425
b111010 B
1.
#426
0.
#427
b111011 B
1.
#428
0.
#429
b111100 B
1.
#430
0.
#431
b111101 B
1.
#432
0.
#433
b111110 B
1.
#434
0.
#435
b111111 B
1.
#436
0.
#437
b1000000 B
1.
#438
0.
#439
b1000001 B
1.
#440
0.
#441
b1000010 B
1.
#442
0.
#443
b1000011 B
1.
#444
0.
#445
b1000100 B
1.
#446
0.
#447
b1000101 B
1.
#448
0.
#449
b1000110 B
1.
#450
0.
#451
b1000111 B
1.
#452
0.
#453
b1001000 B
1.
#454
0.
#455
b1001001 B
1.
#456
0.
#457
b1001010 B
1.
#458
0.
#459
b1001011 B
1.
#460
0.
#461
b1001100 B
1.
#462
0.
#463
b1001101 B
1.
#464
0.
#465
b1001110 B
1.
#466
0.
#467
b1001111 B
1.
#468
0.
#469
b1010000 B
1.
#470
0.
#471
b1010001 B
1.
#472
0.
#473
b1010010 B
1.
#474
0.
#475
b1010011 B
1.
#476
0.
#477
b1010100 B
1.
#478
0.
#479
b1010101 B
1.
#480
0.
#481
b1010110 B
1.
#482
0.
#483
b1010111 B
1.
#484
0.
#485
b1011000 B
1.
#486
0.
#487
b1011001 B
1.
#488
0.
#489
b1011010 B
1.
#490
0.
#491
b1011011 B
1.
#492
0.
#493
b1011100 B
1.
#494
0.
#495
b1011101 B
1.
#496
0.
#497
b1011110 B
1.
#498
0.
#499
b1011111 B
1.
#500
0.
#501
b1100000 B
1.
#502
0.
#503
b1100001 B
1.
#504
0.
#505
b1100010 B
1.
#506
0.
#507
b1100011 B
1.
#508
0.
#509
1#
b0 B
1.
#510
0.
#511
b1 B
1.
#512
0.
#513
b10 B
1.
#514
0.
#515
b11 B
1.
#516
0.
#517
b100 B
1.
#518
0.
#519
b101 B
1.
#520
0.
#521
b110 B
1.
#522
0.
#523
b111 B
1.
#524
0.
#525
b1000 B
1.
#526
0.
#527
0#
b1001 B
1.
#528
0.
#529
b1010 B
1.
#530
0.
#531
b1011 B
1.
#532
0.
#533
b1100 B
1.
#534
0.
#535
b1101 B
1.
#536
0.
#537
b1110 B
1.
#538
0.
#539
b1111 B
1.
#540
0.
#541
b10000 B
1.
#542
0.
#543
b10001 B
1.
#544
0.
#545
b10010 B
1.
#546
0.
#547
b10011 B
1.
#548
0.
#549
b10100 B
1.
#550
0.
#551
b10101 B
1.
#552
0.
#553
b10110 B
1.
#554
0.
#555
b10111 B
1.
#556
0.
#557
b11000 B
1.
#558
0.
#559
b11001 B
1.
#560
0.
#561
b11010 B
1.
#562
0.
#563
b11011 B
1.
#564
0.
#565
b11100 B
1.
#566
0.
#567
b11101 B
1.
#568
0.
#569
b11110 B
1.
#570
0.
#571
b11111 B
1.
#572
0.
#573
b100000 B
1.
#574
0.
#575
b100001 B
1.
#576
0.
#577
b100010 B
1.
#578
0.
#579
b100011 B
1.
#580
0.
#581
b100100 B
1.
#582
0.
#583
b100101 B
1.
#584
0.
#585
b100110 B
1.
#586
0.
#587
b100111 B
1.
#588
0.
#589
b101000 B
1.
#590
0.
#591
b101001 B
1.
#592
0.
#593
b101010 B
1.
#594
0.
#595
b101011 B
1.
#596
0.
#597
b101100 B
1.
#598
0.
#599
b101101 B
1.
#600
0.
#601
b101110 B
1.
#602
0.
#603
b101111 B
1.
#604
0.
#605
b110000 B
1.
#606
0.
#607
b110001 B
1.
#608
0.
#609
b110010 B
1.
#610
0.
#611
b110011 B
1.
#612
0.
#613
b110100 B
1.
#614
0.
#615
b110101 B
1.
#616
0.
#617
b110110 B
1.
#618
0.
#619
b110111 B
1.
#620
0.
#621
b111000 B
1.
#622
0.
#623
b111001 B
1.
#624
0.
#625
b111010 B
1.
#626
0.
#627
b111011 B
1.
#628
0.
#629
b111100 B
1.
#630
0.
#631
b111101 B
1.
#632
0.
#633
b111110 B
1.
#634
0.
#635
b111111 B
1.
#636
0.
#637
b1000000 B
1.
#638
0.
#639
b1000001 B
1.
#640
0.
#641
b1000010 B
1.
#642
0.
#643
b1000011 B
1.
#644
0.
#645
b1000100 B
1.
#646
0.
#647
b1000101 B
1.
#648
0.
#649
b1000110 B
1.
#650
0.
#651
b1000111 B
1.
#652
0.
#653
b1001000 B
1.
#654
0.
#655
b1001001 B
1.
#656
0.
#657
b1001010 B
1.
#658
0.
#659
b1001011 B
1.
#660
0.
#661
b1001100 B
1.
#662
0.
#663
b1001101 B
1.
#664
0.
#665
b1001110 B
1.
#666
0.
#667
b1001111 B
1.
#668
0.
#669
b1010000 B
1.
#670
0.
#671
b1010001 B
1.
#672
0.
#673
b1010010 B
1.
#674
0.
#675
b1010011 B
1.
#676
0.
#677
b1010100 B
1.
#678
0.
#679
b1010101 B
1.
#680
0.
#681
b1010110 B
1.
#682
0.
#683
b1010111 B
1.
#684
0.
#685
b1011000 B
1.
#686
0.
#687
b1011001 B
1.
#688
0.
#689
b1011010 B
1.
#690
0.
#691
b1011011 B
1.
#692
0.
#693
b1011100 B
1.
#694
0.
#695
b1011101 B
1.
#696
0.
#697
b1011110 B
1.
#698
0.
#699
b1011111 B
1.
#700
0.
#701
b1100000 B
1.
#702
0.
#703
b1100001 B
1.
#704
0.
#705
b1100010 B
1.
#706
0.
#707
b1100011 B
1.
#708
0.
#709
1#
b0 B
1.
#710
0.
#711
b1 B
1.
#712
0.
#713
b10 B
1.
#714
0.
#715
b11 B
1.
#716
0.
#717
b100 B
1.
#718
0.
#719
b101 B
1.
#720
0.
#721
b110 B
1.
#722
0.
#723
b111 B
1.
#724
0.
#725
b1000 B
1.
#726
0.
#727
0#
b1001 B
1.
#728
0.
#729
b1010 B
1.
#730
0.
#731
b1011 B
1.
#732
0.
#733
b1100 B
1.
#734
0.
#735
b1101 B
1.
#736
0.
#737
b1110 B
1.
#738
0.
#739
b1111 B
1.
#740
0.
#741
b10000 B
1.
#742
0.
#743
b10001 B
1.
#744
0.
#745
b10010 B
1.
#746
0.
#747
b10011 B
1.
#748
0.
#749
b10100 B
1.
#750
0.
#751
b10101 B
1.
#752
0.
#753
b10110 B
1.
#754
0.
#755
b10111 B
1.
#756
0.
#757
b11000 B
1.
#758
0.
#759
b11001 B
1.
#760
0.
#761
b11010 B
1.
#762
0.
#763
b11011 B
1.
#764
0.
#765
b11100 B
1.
#766
0.
#767
b11101 B
1.
#768
0.
#769
b11110 B
1.
#770
0.
#771
b11111 B
1.
#772
0.
#773
b100000 B
1.
#774
0.
#775
b100001 B
1.
#776
0.
#777
b100010 B
1.
#778
0.
#779
b100011 B
1.
#780
0.
#781
b100100 B
1.
#782
0.
#783
b100101 B
1.
#784
0.
#785
b100110 B
1.
#786
0.
#787
b100111 B
1.
#788
0.
#789
b101000 B
1.
#790
0.
#791
b101001 B
1.
#792
0.
#793
b101010 B
1.
#794
0.
#795
b101011 B
1.
#796
0.
#797
b101100 B
1.
#798
0.
#799
b101101 B
1.
#800
0.
#801
b101110 B
1.
#802
0.
#803
b101111 B
1.
#804
0.
#805
b110000 B
1.
#806
0.
#807
b110001 B
1.
#808
0.
#809
b110010 B
1.
#810
0.
#811
b110011 B
1.
#812
0.
#813
b110100 B
1.
#814
0.
#815
b110101 B
1.
#816
0.
#817
b110110 B
1.
#818
0.
#819
b110111 B
1.
#820
0.
#821
b111000 B
1.
#822
0.
#823
b111001 B
1.
#824
0.
#825
b111010 B
1.
#826
0.
#827
b111011 B
1.
#828
0.
#829
b111100 B
1.
#830
0.
#831
b111101 B
1.
#832
0.
#833
b111110 B
1.
#834
0.
#835
b111111 B
1.
#836
0.
#837
b1000000 B
1.
#838
0.
#839
b1000001 B
1.
#840
0.
#841
b1000010 B
1.
#842
0.
#843
b1000011 B
1.
#844
0.
#845
b1000100 B
1.
#846
0.
#847
b1000101 B
1.
#848
0.
#849
b1000110 B
1.
#850
0.
#851
b1000111 B
1.
#852
0.
#853
b1001000 B
1.
#854
0.
#855
b1001001 B
1.
#856
0.
#857
b1001010 B
1.
#858
0.
#859
b1001011 B
1.
#860
0.
#861
b1001100 B
1.
#862
0.
#863
b1001101 B
1.
#864
0.
#865
b1001110 B
1.
#866
0.
#867
b1001111 B
1.
#868
0.
#869
b1010000 B
1.
#870
0.
#871
b1010001 B
1.
#872
0.
#873
b1010010 B
1.
#874
0.
#875
b1010011 B
1.
#876
0.
#877
b1010100 B
1.
#878
0.
#879
b1010101 B
1.
#880
0.
#881
b1010110 B
1.
#882
0.
#883
b1010111 B
1.
#884
0.
#885
b1011000 B
1.
#886
0.
#887
b1011001 B
1.
#888
0.
#889
b1011010 B
1.
#890
0.
#891
b1011011 B
1.
#892
0.
#893
b1011100 B
1.
#894
0.
#895
b1011101 B
1.
#896
0.
#897
b1011110 B
1.
#898
0.
#899
b1011111 B
1.
#900
0.
#901
b1100000 B
1.
#902
0.
#903
b1100001 B
1.
#904
0.
#905
b1100010 B
1.
#906
0.
#907
b1100011 B
1.
#908
0.
#909
1#
b0 B
1.
#910
0.
#911
b1 B
1.
#912
0.
#913
b10 B
1.
#914
0.
#915
b11 B
1.
#916
0.
#917
b100 B
1.
#918
0.
#919
b101 B
1.
#920
0.
#921
b110 B
1.
#922
0.
#923
b111 B
1.
#924
0.
#925
b1000 B
1.
#926
0.
#927
0#
b1001 B
1.
#928
0.
#929
b1010 B
1.
#930
0.
#931
b1011 B
1.
#932
0.
#933
b1100 B
1.
#934
0.
#935
b1101 B
1.
#936
0.
#937
b1110 B
1.
#938
0.
#939
b1111 B
1.
#940
0.
#941
b10000 B
1.
#942
0.
#943
b10001 B
1.
#944
0.
#945
b10010 B
1.
#946
0.
#947
b10011 B
1.
#948
0.
#949
b10100 B
1.
#950
0.
#951
b10101 B
1.
#952
0.
#953
b10110 B
1.
#954
0.
#955
b10111 B
1.
#956
0.
#957
b11000 B
1.
#958
0.
#959
b11001 B
1.
#960
0.
#961
b11010 B
1.
#962
0.
#963
b11011 B
1.
#964
0.
#965
b11100 B
1.
#966
0.
#967
b11101 B
1.
#968
0.
#969
b11110 B
1.
#970
0.
#971
b11111 B
1.
#972
0.
#973
b100000 B
1.
#974
0.
#975
b100001 B
1.
#976
0.
#977
b100010 B
1.
#978
0.
#979
b100011 B
1.
#980
0.
#981
b100100 B
1.
#982
0.
#983
b100101 B
1.
#984
0.
#985
b100110 B
1.
#986
0.
#987
b100111 B
1.
#988
0.
#989
b101000 B
1.
#990
0.
#991
b101001 B
1.
#992
0.
#993
b101010 B
1.
#994
0.
#995
b101011 B
1.
#996
0.
#997
b101100 B
1.
#998
0.
#999
b101101 B
1.
#1000
0.
#1001
b101110 B
1.
#1002
0.
#1003
b101111 B
1.
#1004
0.
#1005
b110000 B
1.
#1006
0.
#1007
b110001 B
1.
#1008
0.
#1009
b110010 B
1.
#1010
0.
#1011
b110011 B
1.
#1012
0.
#1013
b110100 B
1.
#1014
0.
#1015
b110101 B
1.
#1016
0.
#1017
b110110 B
1.
#1018
0.
#1019
b110111 B
1.
#1020
0.
#1021
b111000 B
1.
#1022
0.
#1023
b111001 B
1.
#1024
0.
#1025
b111010 B
1.
#1026
0.
#1027
b111011 B
1.
#1028
0.
#1029
b111100 B
1.
#1030
0.
#1031
b111101 B
1.
#1032
0.
#1033
b111110 B
1.
#1034
0.
#1035
b111111 B
1.
#1036
0.
#1037
b1000000 B
1.
#1038
0.
#1039
b1000001 B
1.
#1040
0.
#1041
b1000010 B
1.
#1042
0.
#1043
b1000011 B
1.
#1044
0.
#1045
b1000100 B
1.
#1046
0.
#1047
b1000101 B
1.
#1048
0.
#1049
b1000110 B
1.
#1050
0.
#1051
b1000111 B
1.
#1052
0.
#1053
b1001000 B
1.
#1054
0.
#1055
b1001001 B
1.
#1056
0.
#1057
b1001010 B
1.
#1058
0.
#1059
b1001011 B
1.
#1060
0.
#1061
b1001100 B
1.
#1062
0.
#1063
b1001101 B
1.
#1064
0.
#1065
b1001110 B
1.
#1066
0.
#1067
b1001111 B
1.
#1068
0.
#1069
b1010000 B
1.
#1070
0.
#1071
b1010001 B
1.
#1072
0.
#1073
b1010010 B
1.
#1074
0.
#1075
b1010011 B
1.
#1076
0.
#1077
b1010100 B
1.
#1078
0.
#1079
b1010101 B
1.
#1080
0.
#1081
b1010110 B
1.
#1082
0.
#1083
b1010111 B
1.
#1084
0.
#1085
b1011000 B
1.
#1086
0.
#1087
b1011001 B
1.
#1088
0.
#1089
b1011010 B
1.
#1090
0.
#1091
b1011011 B
1.
#1092
0.
#1093
b1011100 B
1.
#1094
0.
#1095
b1011101 B
1.
#1096
0.
#1097
b1011110 B
1.
#1098
0.
#1099
b1011111 B
1.
#1100
0.
#1101
b1100000 B
1.
#1102
0.
#1103
b1100001 B
1.
#1104
0.
#1105
b1100010 B
1.
#1106
0.
#1107
b1100011 B
1.
#1108
0.
#1109
1#
b0 B
1.
#1110
b0 0
0.
1!
b10111010010000111011011101 /
b0 (
#1111
b1 B
1.
